rlai/__init__.py
rlai/core/__init__.py
rlai/core/environments/__init__.py
rlai/core/environments/bandit.py
rlai/core/environments/gamblers_problem.py
rlai/core/environments/gridworld.py
rlai/core/environments/gymnasium.py
rlai/core/environments/mancala.py
rlai/core/environments/mdp.py
rlai/core/environments/network.py
rlai/core/environments/robocode.py
rlai/core/environments/robocode_continuous_action.py
"rlai/figures/Epsilon-greedy with decreasing epsilon, bandit.pdf"
"rlai/figures/Epsilon-greedy with recency-weighted reward average, nonstationary bandit.pdf"
"rlai/figures/Epsilon-greedy, nonstationary bandit.pdf"
"rlai/figures/Figure 2.2: Epsilon-greedy, bandit.pdf"
"rlai/figures/Figure 2.3:  Greedy with optimistic initial values and recency-weighted reward average, bandit.pdf"
"rlai/figures/Figure 2.4:  Upper confidence bound, bandit.pdf"
"rlai/figures/Figure 2.5:  Preference gradient no baseline, bandit.pdf"
"rlai/figures/Figure 2.5:  Preference gradient, bandit.pdf"
rlai/figures/Mancala Learning.png
"rlai/figures/Quick run:  Epsilon-greedy, bandit.pdf"
rlai/gpi/__init__.py
rlai/gpi/dynamic_programming/__init__.py
rlai/gpi/dynamic_programming/evaluation.py
rlai/gpi/dynamic_programming/iteration.py
rlai/gpi/monte_carlo/__init__.py
rlai/gpi/monte_carlo/evaluation.py
rlai/gpi/monte_carlo/iteration.py
rlai/gpi/state_action_value/__init__.py
rlai/gpi/state_action_value/function_approximation/__init__.py
rlai/gpi/state_action_value/function_approximation/models/__init__.py
rlai/gpi/state_action_value/function_approximation/models/feature_extraction.py
rlai/gpi/state_action_value/function_approximation/models/sklearn.py
rlai/gpi/state_action_value/tabular.py
rlai/gpi/temporal_difference/__init__.py
rlai/gpi/temporal_difference/evaluation.py
rlai/gpi/temporal_difference/iteration.py
rlai/gpi/utils.py
rlai/meta.py
rlai/models/__init__.py
rlai/models/feature_extraction.py
rlai/models/sklearn.py
rlai/plot_utils.py
rlai/policy_gradient/__init__.py
rlai-1.4.0.dist-info/LICENSE
rlai-1.4.0.dist-info/METADATA
rlai-1.4.0.dist-info/WHEEL
rlai-1.4.0.dist-info/entry_points.txt
rlai-1.4.0.dist-info/RECORD
