Metadata-Version: 2.1
Name: rlai
Version: 1.4.0
Summary: Reinforcement Learning:  An Introduction
Home-page: https://github.com/MatthewGerber/rlai
Author: Matthew Gerber
Author-email: gerber.matthew@gmail.com
Requires-Python: >=3.10,<3.13
Classifier: Programming Language :: Python :: 3
Classifier: Programming Language :: Python :: 3.10
Classifier: Programming Language :: Python :: 3.11
Classifier: Programming Language :: Python :: 3.12
Requires-Dist: PyQt6 (>=6.7,<7.0) ; platform_machine != "aarch64"
Requires-Dist: gymnasium[box2d,classic-control,mujoco] (==1.0.0a2)
Requires-Dist: ipython (>=8.25,<9.0)
Requires-Dist: jax[cpu] (>=0.4,<1.0)
Requires-Dist: jupyterlab (>=4.2,<5.0)
Requires-Dist: matplotlib (>=3.9,<4.0)
Requires-Dist: moviepy (>=1.0,<2.0)
Requires-Dist: numpy (>=1.26,<2.0)
Requires-Dist: pandas (>=2.2,<3.0)
Requires-Dist: patsy (>=0.5,<1.0)
Requires-Dist: pyqtgraph (>=0.13,<1.0)
Requires-Dist: scikit-learn (>=1.5,<2.0)
Requires-Dist: scipy (>=1.13,<2.0)
Requires-Dist: tabulate (>=0.9,<1.0)
Requires-Dist: types-requests (>=2.32.0.20240712,<3.0.0.0)
Requires-Dist: types-tabulate (>=0.9.0.20240106,<0.10.0.0)
Project-URL: Repository, https://github.com/MatthewGerber/rlai
